trolleer/__init__.py
trolleer-0.0.1.dist-info/METADATA
trolleer-0.0.1.dist-info/WHEEL
trolleer-0.0.1.dist-info/top_level.txt
trolleer-0.0.1.dist-info/RECORD
