Metadata-Version: 2.1
Name: trolleer
Version: 0.0.1
Summary: Use import trolleer to import package and pip unistall to uninstall package if you don't like it.
Home-page: UNKNOWN
Author: WebSoft-tech
Author-email: 
License: UNKNOWN
Platform: UNKNOWN
Classifier: Programming Language :: Python :: 3
Classifier: License :: OSI Approved :: MIT License
Classifier: Operating System :: Microsoft :: Windows :: Windows 10
Requires-Python: >=3.6
